.gitignore
.readthedocs.yaml
CMakeLists.txt
CODE_OF_CONDUCT.md
DCO
Dockerfile
Dockerfile.openEuler
LICENSE
README.md
README.zh.md
format.sh
mypy.ini
packages.txt
pyproject.toml
pytest.ini
requirements-dev.txt
requirements-lint.txt
requirements.txt
setup.py
.github/PULL_REQUEST_TEMPLATE.md
.github/dependabot.yml
.github/labeler.yml
.github/ISSUE_TEMPLATE/100-documentation.yml
.github/ISSUE_TEMPLATE/200-installation.yml
.github/ISSUE_TEMPLATE/300-usage.yml
.github/ISSUE_TEMPLATE/400-bug-report.yml
.github/ISSUE_TEMPLATE/500-feature-request.yml
.github/ISSUE_TEMPLATE/600-new-model.yml
.github/ISSUE_TEMPLATE/700-performance-discussion.yml
.github/ISSUE_TEMPLATE/750-RFC.yml
.github/ISSUE_TEMPLATE/800-others.yml
.github/ISSUE_TEMPLATE/config.yml
.github/workflows/actionlint.yml
.github/workflows/image_openeuler.yml
.github/workflows/image_ubuntu.yml
.github/workflows/labeler.yml
.github/workflows/mypy.yaml
.github/workflows/ruff.yml
.github/workflows/shellcheck.yml
.github/workflows/vllm_ascend_test.yaml
.github/workflows/yapf.yml
.github/workflows/matchers/actionlint.json
.github/workflows/matchers/mypy.json
.github/workflows/matchers/ruff.json
benchmarks/README.md
benchmarks/requirements-bench.txt
benchmarks/scripts/run-performance-benchmarks.sh
benchmarks/tests/latency-tests.json
benchmarks/tests/serving-tests.json
benchmarks/tests/throughput-tests.json
cmake/utils.cmake
cmq_test.egg-info/PKG-INFO
cmq_test.egg-info/SOURCES.txt
cmq_test.egg-info/dependency_links.txt
cmq_test.egg-info/entry_points.txt
cmq_test.egg-info/requires.txt
cmq_test.egg-info/top_level.txt
csrc/camem_allocator.cpp
csrc/ops.h
csrc/torch_binding.cpp
csrc/utils.h
csrc/kernels/pos_encoding_kernels.cpp
csrc/kernels/types.h
csrc/kernels/utils.h
docs/Makefile
docs/README.md
docs/requirements-docs.txt
docs/requirements-test.txt
docs/source/conf.py
docs/source/faqs.md
docs/source/index.md
docs/source/installation.md
docs/source/quick_start.md
docs/source/developer_guide/contributing.md
docs/source/developer_guide/contributing.zh.md
docs/source/developer_guide/versioning_policy.md
docs/source/developer_guide/versioning_policy.zh.md
docs/source/developer_guide/evaluation/index.md
