Metadata-Version: 2.4
Name: cmq-test
Version: 0.8.3
Summary: vLLM Ascend backend plugin
Home-page: https://github.com/vllm-project/vllm-ascend
Author: vLLM-Ascend team
License: Apache 2.0
Project-URL: Homepage, https://github.com/vllm-project/vllm-ascend
Classifier: Programming Language :: Python :: 3.9
Classifier: Programming Language :: Python :: 3.10
Classifier: Programming Language :: Python :: 3.11
Classifier: Programming Language :: Python :: 3.12
Classifier: License :: OSI Approved :: Apache Software License
Classifier: Intended Audience :: Developers
Classifier: Intended Audience :: Information Technology
Classifier: Intended Audience :: Science/Research
Classifier: Topic :: Scientific/Engineering :: Artificial Intelligence
Classifier: Topic :: Scientific/Engineering :: Information Analysis
Requires-Python: >=3.9
License-File: LICENSE
Requires-Dist: cmake>=3.26
Requires-Dist: decorator
Requires-Dist: numpy<2.0.0
Requires-Dist: packaging
Requires-Dist: pip
Requires-Dist: pybind11
Requires-Dist: pyyaml
Requires-Dist: scipy
Requires-Dist: setuptools>=64
Requires-Dist: setuptools-scm>=8
Requires-Dist: torch-npu==2.5.1
Requires-Dist: torch>=2.5.1
Requires-Dist: torchvision<0.21.0
Requires-Dist: wheel
Provides-Extra: mindie-turbo
Requires-Dist: mindie-turbo==2.0rc1; extra == "mindie-turbo"
Dynamic: author
Dynamic: classifier
Dynamic: description
Dynamic: description-content-type
Dynamic: home-page
Dynamic: license
Dynamic: license-file
Dynamic: project-url
Dynamic: provides-extra
Dynamic: requires-dist
Dynamic: requires-python
Dynamic: summary
